apafea/__init__.py
apafea/__main__.py
apafea/sample_data/BiCoN/results.csv
apafea/sample_data/KPM/Pathway-01-NODES-.txt
apafea/sample_data/KPM/Pathway-02-NODES-.txt
apafea/sample_data/KPM/Pathway-03-NODES-.txt
apafea/sample_data/KPM/Pathway-04-NODES-.txt
apafea/sample_data/KPM/Pathway-05-NODES-.txt
apafea/sample_data/KPM/Pathway-06-NODES-.txt
apafea/sample_data/KPM/Pathway-07-NODES-.txt
apafea/sample_data/KPM/Pathway-08-NODES-.txt
apafea/sample_data/KPM/Pathway-09-NODES-.txt
apafea/sample_data/KPM/Pathway-10-NODES-.txt
apafea/sample_data/KPM/Pathway-11-NODES-.txt
apafea/sample_data/KPM/Pathway-12-NODES-.txt
apafea/sample_data/KPM/Pathway-13-NODES-.txt
apafea/sample_data/KPM/Pathway-14-NODES-.txt
apafea/sample_data/KPM/Pathway-15-NODES-.txt
apafea/sample_data/KPM/Pathway-16-NODES-.txt
apafea/sample_data/KPM/Pathway-17-NODES-.txt
apafea/sample_data/KPM/Pathway-18-NODES-.txt
apafea/sample_data/KPM/Pathway-19-NODES-.txt
apafea/sample_data/KPM/Pathway-20-NODES-.txt
apafea/src/__init__.py
apafea/src/apafea.py
apafea-0.0.9.dist-info/LICENSE.txt
apafea-0.0.9.dist-info/METADATA
apafea-0.0.9.dist-info/WHEEL
apafea-0.0.9.dist-info/entry_points.txt
apafea-0.0.9.dist-info/top_level.txt
apafea-0.0.9.dist-info/RECORD
