Metadata-Version: 2.1
Name: apafea
Version: 0.0.9
Summary: visualizes genes functional enrichment
Home-page: https://gitlab2.cip.ifi.lmu.de/puerckhauer/apafea
Author: Korbinian Pürckhauer
Author-email: korbinian@puerckhauer.net
Maintainer: Korbinian Pürckhauer
Maintainer-email: korbinian@puerckhauer.net
License: MIT
Download-URL: https://gitlab2.cip.ifi.lmu.de/puerckhauer/apafea
Project-URL: Bug tracker, https://gitlab2.cip.ifi.lmu.de/puerckhauer/apafea
Keywords: gene,enrichment,alluvial,sankey,bioinformatics
Platform: UNKNOWN
Classifier: Operating System :: Microsoft :: Windows
Classifier: Operating System :: MacOS
Classifier: Programming Language :: Python
Classifier: Intended Audience :: Science/Research
Classifier: Topic :: Scientific/Engineering :: Bio-Informatics
Requires-Python: >=3.10
License-File: LICENSE.txt
